MANIFEST.in
README.md
setup.py
phred/ChangeRecord.py
phred/EditWin.py
phred/Editor.py
phred/Keyboard.py
phred/Menu.py
phred/Pairs.py
phred/Phred.py
phred/Piper.py
phred/SearchReplace.py
phred/Selector.py
phred/UiComponents.py
phred/__init__.py
phred/foo.py
phred/tags.py
phred.egg-info/PKG-INFO
phred.egg-info/SOURCES.txt
phred.egg-info/dependency_links.txt
phred.egg-info/entry_points.txt
phred.egg-info/not-zip-safe
phred.egg-info/requires.txt
phred.egg-info/top_level.txt
phred/tests/__init__.py
phred/tests/test_phred.py