Metadata-Version: 2.1
Name: phred
Version: 1.0.0
Summary: Phred text editor
Home-page: http://bitbucket.org/garry/phred
Author: Garry Hodgson
Author-email: garry@snarkus.com
License: MIT
Keywords: phred text editor tools article python package
Platform: UNKNOWN
Classifier: Programming Language :: Python :: 3
Classifier: License :: OSI Approved :: MIT License
Classifier: Operating System :: OS Independent
